setup.py
blended_facebook_cards.egg-info/PKG-INFO
blended_facebook_cards.egg-info/SOURCES.txt
blended_facebook_cards.egg-info/dependency_links.txt
blended_facebook_cards.egg-info/not-zip-safe
blended_facebook_cards.egg-info/requires.txt
blended_facebook_cards.egg-info/top_level.txt
facebook_cards/__init__.py